setup.cfg
setup.py
wtouch/__init__.py
wtouch/main.py
wtouch/touch.py
wtouch.egg-info/PKG-INFO
wtouch.egg-info/SOURCES.txt
wtouch.egg-info/dependency_links.txt
wtouch.egg-info/entry_points.txt
wtouch.egg-info/top_level.txt