Metadata-Version: 1.0
Name: wtouch
Version: 0.0.1
Summary: Create a file in current folder.
Home-page: https://github.com/Frederick-S/wtouch
Author: UNKNOWN
Author-email: UNKNOWN
License: UNKNOWN
Platform: UNKNOWN
